bam/__init__.py
bam/__init__.pyc
bam/__main__.py
bam/cli.py
bam/no__main.py
bam/pack.py
bam/blend/__init__.py
bam/blend/blendfile.py
bam/blend/blendfile_copy.py
bam/blend/blendfile_pack.py
bam/blend/blendfile_pack_restore.py
bam/blend/blendfile_path_remap.py
bam/blend/blendfile_path_walker.py
bam/utils/__init__.py
bam/utils/system.py
blender_bam-1.1.7.dist-info/DESCRIPTION.rst
blender_bam-1.1.7.dist-info/METADATA
blender_bam-1.1.7.dist-info/RECORD
blender_bam-1.1.7.dist-info/WHEEL
blender_bam-1.1.7.dist-info/entry_points.txt
blender_bam-1.1.7.dist-info/metadata.json
blender_bam-1.1.7.dist-info/top_level.txt
